XinbianWin32apiDaquan/README.md
XinbianWin32apiDaquan/__init__.py
XinbianWin32apiDaquan/__main__.py
XinbianWin32apiDaquan/file.epub
XinbianWin32apiDaquan/index.html
XinbianWin32apiDaquan/css/__init__.py
XinbianWin32apiDaquan/css/annotations.css
XinbianWin32apiDaquan/css/main.css
XinbianWin32apiDaquan/css/normalize.css
XinbianWin32apiDaquan/css/popup.css
XinbianWin32apiDaquan/font/__init__.py
XinbianWin32apiDaquan/font/fontello.eot
XinbianWin32apiDaquan/font/fontello.svg
XinbianWin32apiDaquan/font/fontello.ttf
XinbianWin32apiDaquan/font/fontello.woff
XinbianWin32apiDaquan/img/__init__.py
XinbianWin32apiDaquan/img/annotator-glyph-sprite.png
XinbianWin32apiDaquan/img/annotator-icon-sprite.png
XinbianWin32apiDaquan/img/apple-touch-icon.png
XinbianWin32apiDaquan/img/cancelfullscreen.png
XinbianWin32apiDaquan/img/close.png
XinbianWin32apiDaquan/img/fullscreen.png
XinbianWin32apiDaquan/img/loader.gif
XinbianWin32apiDaquan/img/menu-icon.png
XinbianWin32apiDaquan/img/save.png
XinbianWin32apiDaquan/img/saved.png
XinbianWin32apiDaquan/img/settings-s.png
XinbianWin32apiDaquan/img/settings.png
XinbianWin32apiDaquan/img/star.png
XinbianWin32apiDaquan/js/__init__.py
XinbianWin32apiDaquan/js/epub.js
XinbianWin32apiDaquan/js/epub.min.js
XinbianWin32apiDaquan/js/epub.min.map
XinbianWin32apiDaquan/js/hooks.min.js
XinbianWin32apiDaquan/js/hooks.min.map
XinbianWin32apiDaquan/js/reader.js
XinbianWin32apiDaquan/js/reader.js.map
XinbianWin32apiDaquan/js/reader.min.js
XinbianWin32apiDaquan/js/reader.min.map
XinbianWin32apiDaquan/js/hooks/__init__.py
XinbianWin32apiDaquan/js/hooks/extensions/__init__.py
XinbianWin32apiDaquan/js/hooks/extensions/highlight.js
XinbianWin32apiDaquan/js/libs/__init__.py
XinbianWin32apiDaquan/js/libs/jquery.min.js
XinbianWin32apiDaquan/js/libs/localforage.min.js
XinbianWin32apiDaquan/js/libs/screenfull.js
XinbianWin32apiDaquan/js/libs/screenfull.min.js
XinbianWin32apiDaquan/js/libs/zip.min.js
XinbianWin32apiDaquan/js/plugins/__init__.py
xinbian_win32api_daquan-2024.2.29.0.dist-info/METADATA
xinbian_win32api_daquan-2024.2.29.0.dist-info/WHEEL
xinbian_win32api_daquan-2024.2.29.0.dist-info/entry_points.txt
xinbian_win32api_daquan-2024.2.29.0.dist-info/top_level.txt
xinbian_win32api_daquan-2024.2.29.0.dist-info/RECORD
